argument_mining_framework/__init__.py
argument_mining_framework/loader.py
argument_mining_framework/argument_relation/__init__.py
argument_mining_framework/argument_relation/predictor.py
argument_mining_framework/argument_relation/dam/__init__.py
argument_mining_framework/argument_relation/dam/data.py
argument_mining_framework/argument_relation/dam/models.py
argument_mining_framework/argument_relation/dam/templates.py
argument_mining_framework/argument_relation/dam/utility.py
argument_mining_framework/argument_relation/dam/ArgumentRelationAnalyser/__init__.py
argument_mining_framework/argument_relation/dam/ArgumentRelationAnalyser/dam1_features_map.py
argument_mining_framework/argument_relation/dam/ArgumentRelationAnalyser/dam2_features_map.py
argument_mining_framework/argument_relation/dam/ArgumentRelationAnalyser/dam3_features_map.py
argument_mining_framework/argument_relation/dam/ArgumentRelationAnalyser/predictor.py
argument_mining_framework/argument_relation/dam/config/config.json
argument_mining_framework/argument_relation/dam/config/dct_exapand.txt
argument_mining_framework/argument_relation/dam/config/spacy_tag_dep.csv
argument_mining_framework/argument_relation/dam/decompose/__init__.py
argument_mining_framework/argument_relation/dam/decompose/get_components.py
argument_mining_framework/argument_relation/dam/decompose/subject_verb_object_extract.py
argument_mining_framework/argument_relation/dam/decompose/svo_patterns.py
argument_mining_framework/argument_relation/dam/decompose/token_clasifier_inference.py
argument_mining_framework/argument_relation/dam/decompose/tt.py
argument_mining_framework/argument_relation/dam/features/entailment.py
argument_mining_framework/argument_relation/dam/features/sentiment.py
argument_mining_framework/argument_relation/dam/features/similarity.py
argument_mining_framework/argument_relation/sequence_classifier/__init__.py
argument_mining_framework/argument_relation/sequence_classifier/config.json
argument_mining_framework-0.1.9.dist-info/METADATA
argument_mining_framework-0.1.9.dist-info/WHEEL
argument_mining_framework-0.1.9.dist-info/RECORD
