Metadata-Version: 2.3
Name: argument_mining_framework
Version: 0.1.9
Summary: Argument Mining Framework (AMF) is a comprehensive toolkit designed to streamline and unify various argument mining modules into a single platform.
Project-URL: Homepage, https://github.com/orgs/arg-tech/projects/2
Project-URL: Issues, https://github.com/arg-tech/amf/issues
Project-URL: Documentation, https://wiki.arg.tech/books/amf
Project-URL: Source, https://github.com/arg-tech/amf
Author-email: Debela <d.t.z.gemechu@dundee.ac.uk>
Classifier: License :: OSI Approved :: MIT License
Classifier: Operating System :: OS Independent
Classifier: Programming Language :: Python :: 3
Classifier: Programming Language :: Python :: 3.8
Classifier: Programming Language :: Python :: 3.9
Classifier: Programming Language :: Python :: 3.10
Classifier: Topic :: Scientific/Engineering :: Artificial Intelligence
Classifier: Topic :: Software Development :: Libraries :: Python Modules
Requires-Python: >=3.8
Requires-Dist: cython
Requires-Dist: nltk
Requires-Dist: numpy
Requires-Dist: pandas
Requires-Dist: scikit-learn
Requires-Dist: sentence-transformers
Requires-Dist: spacy
Requires-Dist: torch
Requires-Dist: transformers
Requires-Dist: xaif-eval==0.1.4
Provides-Extra: all
Requires-Dist: torch; extra == 'all'
Requires-Dist: transformers; extra == 'all'
Provides-Extra: hypothesis
Requires-Dist: torch; extra == 'hypothesis'
Requires-Dist: transformers; extra == 'hypothesis'
Provides-Extra: relation-identifier
Requires-Dist: torch; extra == 'relation-identifier'
Requires-Dist: transformers; extra == 'relation-identifier'
Provides-Extra: scheme
Requires-Dist: torch; extra == 'scheme'
Requires-Dist: transformers; extra == 'scheme'
Provides-Extra: segmenter
Provides-Extra: turninator
Provides-Extra: visualiser
